rcee/__init__.py
rcee/__main__.py
rcee/cli.py
rcee/endpoint.py
rcee/routers/__init__.py
rcee/routers/file.py
rcee/routers/shell.py
rcee/routers/template.py
rcee-0.0.4.dist-info/entry_points.txt
rcee-0.0.4.dist-info/LICENSE
rcee-0.0.4.dist-info/WHEEL
rcee-0.0.4.dist-info/METADATA
rcee-0.0.4.dist-info/RECORD
